dnf.py
dnf-0.0.1.dist-info/LICENSE
dnf-0.0.1.dist-info/WHEEL
dnf-0.0.1.dist-info/METADATA
dnf-0.0.1.dist-info/RECORD
