Metadata-Version: 1.2
Name: dnf
Version: 0.0.1
Summary: Placeholder pending proper publication of DNF Python API
Home-page: https://github.com/ncoghlan/pypi-dnf
License: GPLv2+
Author: DNF developers
Author-email: ncoghlan@gmail.com
Maintainer: Nick Coghlan
Maintainer-email: ncoghlan@gmail.com
